odoo/addons/account_statement_import_online_plaid/README.rst
odoo/addons/account_statement_import_online_plaid/__init__.py
odoo/addons/account_statement_import_online_plaid/__manifest__.py
odoo/addons/account_statement_import_online_plaid/i18n/account_statement_import_online_plaid.pot
odoo/addons/account_statement_import_online_plaid/i18n/es.po
odoo/addons/account_statement_import_online_plaid/i18n/it.po
odoo/addons/account_statement_import_online_plaid/models/__init__.py
odoo/addons/account_statement_import_online_plaid/models/online_bank_statement_provider_plaid.py
odoo/addons/account_statement_import_online_plaid/models/plaid_interface.py
odoo/addons/account_statement_import_online_plaid/readme/CONFIGURE.md
odoo/addons/account_statement_import_online_plaid/readme/CONTRIBUTORS.md
odoo/addons/account_statement_import_online_plaid/readme/DESCRIPTION.md
odoo/addons/account_statement_import_online_plaid/readme/USAGE.md
odoo/addons/account_statement_import_online_plaid/static/description/icon.png
odoo/addons/account_statement_import_online_plaid/static/description/index.html
odoo/addons/account_statement_import_online_plaid/static/description/plaid_keys.png
odoo/addons/account_statement_import_online_plaid/static/src/js/plaid_integration.esm.js
odoo/addons/account_statement_import_online_plaid/static/src/lib/link/v2/stable/link-initialize.js
odoo/addons/account_statement_import_online_plaid/tests/__init__.py
odoo/addons/account_statement_import_online_plaid/tests/test_account_statement_import_online_plaid.py
odoo/addons/account_statement_import_online_plaid/tests/test_plaid_interface.py
odoo/addons/account_statement_import_online_plaid/views/online_bank_statement_provider.xml
odoo_addon_account_statement_import_online_plaid-18.0.1.0.0.4.dist-info/METADATA
odoo_addon_account_statement_import_online_plaid-18.0.1.0.0.4.dist-info/WHEEL
odoo_addon_account_statement_import_online_plaid-18.0.1.0.0.4.dist-info/top_level.txt
odoo_addon_account_statement_import_online_plaid-18.0.1.0.0.4.dist-info/RECORD
